azureml/__init__.py
azureml/contrib/__init__.py
azureml/contrib/fairness/__init__.py
azureml/contrib/fairness/_azureml_validation.py
azureml/contrib/fairness/_common_properties.py
azureml/contrib/fairness/_constants.py
azureml/contrib/fairness/_dashboard_validation.py
azureml/contrib/fairness/_exceptions.py
azureml/contrib/fairness/_fairness_artifact_client.py
azureml/contrib/fairness/_fairness_client.py
azureml/contrib/fairness/_specific_uploaders.py
azureml/contrib/fairness/dashboardDictionary-0.json
azureml_contrib_fairness-1.60.0.dist-info/licenses/LICENSE.txt
azureml_contrib_fairness-1.60.0.dist-info/METADATA
azureml_contrib_fairness-1.60.0.dist-info/WHEEL
azureml_contrib_fairness-1.60.0.dist-info/top_level.txt
azureml_contrib_fairness-1.60.0.dist-info/RECORD
